stockfeat/__init__.py
stockfeat/examples.py
stockfeat/momentum.py
stockfeat/others.py
stockfeat/stockfeat.py
stockfeat/timeseries_normalize_rolling.py
stockfeat/trend.py
stockfeat/volatility.py
stockfeat/volume.py
stockfeat/data/__init__.py
stockfeat-0.1.0.dist-info/LICENSE
stockfeat-0.1.0.dist-info/METADATA
stockfeat-0.1.0.dist-info/WHEEL
stockfeat-0.1.0.dist-info/top_level.txt
stockfeat-0.1.0.dist-info/RECORD
