Metadata-Version: 2.1
Name: stockfeat
Version: 0.1.0
Summary: Python package to create stock related features.
Home-page: https://github.com/erdogant/stockfeat
Author: Erdogan Taskesen
Author-email: erdogant@gmail.com
License: UNKNOWN
Download-URL: https://github.com/erdogant/stockfeat/archive/0.1.0.tar.gz
Platform: UNKNOWN
Classifier: Programming Language :: Python :: 3
Classifier: License :: OSI Approved :: MIT License
Classifier: Operating System :: OS Independent
Requires-Python: >=3
Requires-Dist: wget
Requires-Dist: matplotlib
Requires-Dist: numpy
Requires-Dist: pandas
Requires-Dist: tqdm
Requires-Dist: ta-lib
